{
    "version": "v2.1.0",
    "architecture": {
        "64bit": {
            "url": "https://github.com/brad-jones/gomake/releases/download/v2.1.0/gomake_windows_amd64.exe#/gomake.exe",
            "bin": [
                "gomake.exe"
            ],
            "hash": "ee377798d58260f25ccbceda3dc7fd388ed999ccc4f6a88c6c4e8ac8fd8494c2"
        }
    },
    "homepage": "https://github.com/brad-jones/gomake",
    "license": "MIT",
    "description": "A cross platform build tool / task runner that scales."
}
